<?xml version="1.0" encoding="UTF-8" ?>
<!DOCTYPE mapper PUBLIC "-//mybatis.org//DTD Mapper 3.0//EN" "http://mybatis.org/dtd/mybatis-3-mapper.dtd" >
<mapper namespace="com.whut.wharf.mapper.ExpenseTypeInfoMapper" >
  <resultMap id="BaseResultMap" type="com.whut.wharf.entity.ExpenseTypeInfo" >
    <!--
      WARNING - @mbggenerated
      This element is automatically generated by MyBatis Generator, do not modify.
      This element was generated on Sun Dec 03 17:13:30 CST 2023.
    -->
    <result column="mkey" property="mkey" jdbcType="INTEGER" />
    <result column="expensetype" property="expensetype" jdbcType="VARCHAR" />
    <result column="taxrate" property="taxrate" jdbcType="REAL" />
    <result column="reserve" property="reserve" jdbcType="VARCHAR" />
    <result column="EnglishName" property="englishname" jdbcType="VARCHAR" />
    <result column="CommodityCode" property="commoditycode" jdbcType="VARCHAR" />
    <result column="Unit" property="unit" jdbcType="VARCHAR" />
    <result column="Specifications" property="specifications" jdbcType="VARCHAR" />
    <result column="TaxClassificationCode" property="taxclassificationcode" jdbcType="VARCHAR" />
    <result column="ZeroTaxMark" property="zerotaxmark" jdbcType="VARCHAR" />
    <result column="TaxVersion" property="taxversion" jdbcType="VARCHAR" />
    <result column="PreferentialPolicies" property="preferentialpolicies" jdbcType="VARCHAR" />
    <result column="TaxRelief" property="taxrelief" jdbcType="VARCHAR" />
    <result column="Price" property="price" jdbcType="VARCHAR" />
  </resultMap>
  <insert id="insert" parameterType="com.whut.wharf.entity.ExpenseTypeInfo" >
    <!--
      WARNING - @mbggenerated
      This element is automatically generated by MyBatis Generator, do not modify.
      This element was generated on Sun Dec 03 17:13:30 CST 2023.
    -->
    insert into expensetypeinfo (mkey, expensetype, taxrate, 
      reserve, EnglishName, CommodityCode, 
      Unit, Specifications, TaxClassificationCode, 
      ZeroTaxMark, TaxVersion, PreferentialPolicies, 
      TaxRelief, Price)
    values (#{mkey,jdbcType=INTEGER}, #{expensetype,jdbcType=VARCHAR}, #{taxrate,jdbcType=REAL}, 
      #{reserve,jdbcType=VARCHAR}, #{englishname,jdbcType=VARCHAR}, #{commoditycode,jdbcType=VARCHAR}, 
      #{unit,jdbcType=VARCHAR}, #{specifications,jdbcType=VARCHAR}, #{taxclassificationcode,jdbcType=VARCHAR}, 
      #{zerotaxmark,jdbcType=VARCHAR}, #{taxversion,jdbcType=VARCHAR}, #{preferentialpolicies,jdbcType=VARCHAR}, 
      #{taxrelief,jdbcType=VARCHAR}, #{price,jdbcType=VARCHAR})
  </insert>
  <insert id="insertSelective" parameterType="com.whut.wharf.entity.ExpenseTypeInfo" >
    <!--
      WARNING - @mbggenerated
      This element is automatically generated by MyBatis Generator, do not modify.
      This element was generated on Sun Dec 03 17:13:30 CST 2023.
    -->
    insert into expensetypeinfo
    <trim prefix="(" suffix=")" suffixOverrides="," >
      <if test="mkey != null" >
        mkey,
      </if>
      <if test="expensetype != null" >
        expensetype,
      </if>
      <if test="taxrate != null" >
        taxrate,
      </if>
      <if test="reserve != null" >
        reserve,
      </if>
      <if test="englishname != null" >
        EnglishName,
      </if>
      <if test="commoditycode != null" >
        CommodityCode,
      </if>
      <if test="unit != null" >
        Unit,
      </if>
      <if test="specifications != null" >
        Specifications,
      </if>
      <if test="taxclassificationcode != null" >
        TaxClassificationCode,
      </if>
      <if test="zerotaxmark != null" >
        ZeroTaxMark,
      </if>
      <if test="taxversion != null" >
        TaxVersion,
      </if>
      <if test="preferentialpolicies != null" >
        PreferentialPolicies,
      </if>
      <if test="taxrelief != null" >
        TaxRelief,
      </if>
      <if test="price != null" >
        Price,
      </if>
    </trim>
    <trim prefix="values (" suffix=")" suffixOverrides="," >
      <if test="mkey != null" >
        #{mkey,jdbcType=INTEGER},
      </if>
      <if test="expensetype != null" >
        #{expensetype,jdbcType=VARCHAR},
      </if>
      <if test="taxrate != null" >
        #{taxrate,jdbcType=REAL},
      </if>
      <if test="reserve != null" >
        #{reserve,jdbcType=VARCHAR},
      </if>
      <if test="englishname != null" >
        #{englishname,jdbcType=VARCHAR},
      </if>
      <if test="commoditycode != null" >
        #{commoditycode,jdbcType=VARCHAR},
      </if>
      <if test="unit != null" >
        #{unit,jdbcType=VARCHAR},
      </if>
      <if test="specifications != null" >
        #{specifications,jdbcType=VARCHAR},
      </if>
      <if test="taxclassificationcode != null" >
        #{taxclassificationcode,jdbcType=VARCHAR},
      </if>
      <if test="zerotaxmark != null" >
        #{zerotaxmark,jdbcType=VARCHAR},
      </if>
      <if test="taxversion != null" >
        #{taxversion,jdbcType=VARCHAR},
      </if>
      <if test="preferentialpolicies != null" >
        #{preferentialpolicies,jdbcType=VARCHAR},
      </if>
      <if test="taxrelief != null" >
        #{taxrelief,jdbcType=VARCHAR},
      </if>
      <if test="price != null" >
        #{price,jdbcType=VARCHAR},
      </if>
    </trim>
  </insert>
</mapper>